{
  "_class": "group",
  "booleanOperation": 0,
  "do_objectID": "428AD53B-D309-4D30-A3DF-9B1B2342A268",
  "exportOptions": {
    "_class": "exportOptions",
    "exportFormats": [
    ],
    "includedLayerIds": [
    ],
    "layerOptions": 0,
    "shouldTrim": false
  },
  "frame": {
    "_class": "rect",
    "constrainProportions": false,
    "height": 23,
    "width": 72,
    "x": 0,
    "y": 78
  },
  "hasClickThrough": false,
  "isFixedToViewport": false,
  "isFlippedHorizontal": false,
  "isFlippedVertical": false,
  "isLocked": false,
  "isVisible": true,
  "layerListExpandedType": 1,
  "layers": [
    {
      "class": "shapeGroup",
      "id": "D4C1D291-0AFC-4140-9EA0-F5C81186440C"
    },
    {
      "class": "text",
      "id": "C7C70E1E-2EBA-446D-B6F0-D760C2D59B52"
    }
  ],
  "name": "Dynamic group",
  "nameIsFixed": false,
  "resizingConstraint": 63,
  "resizingType": 0,
  "rotation": 0,
  "shouldBreakMaskChain": false,
  "style": {
    "_class": "style",
    "endMarkerType": 0,
    "miterLimit": 10,
    "startMarkerType": 0,
    "windingRule": 1
  }
}