{
  "_class": "group",
  "booleanOperation": 0,
  "do_objectID": "94AC2FAE-6596-44FE-8D65-5A2021535DE4",
  "exportOptions": {
    "_class": "exportOptions",
    "exportFormats": [
    ],
    "includedLayerIds": [
    ],
    "layerOptions": 0,
    "shouldTrim": false
  },
  "frame": {
    "_class": "rect",
    "constrainProportions": false,
    "height": 21,
    "width": 215,
    "x": 0,
    "y": 49
  },
  "hasClickThrough": false,
  "isFixedToViewport": false,
  "isFlippedHorizontal": false,
  "isFlippedVertical": false,
  "isLocked": false,
  "isVisible": true,
  "layerListExpandedType": 0,
  "layers": [
    {
      "class": "shapeGroup",
      "id": "A82D4555-D800-4B98-8745-63BF5706B331"
    },
    {
      "class": "text",
      "id": "5BB6B9C3-5DEB-4139-9FF5-F5D292218AB0"
    }
  ],
  "name": "discipline",
  "nameIsFixed": true,
  "resizingConstraint": 63,
  "resizingType": 0,
  "rotation": 0,
  "shouldBreakMaskChain": false,
  "style": {
    "_class": "style",
    "endMarkerType": 0,
    "miterLimit": 10,
    "startMarkerType": 0,
    "windingRule": 1
  }
}