{
  "_class": "page",
  "do_objectID": "D9F7CA66-B7EC-47DD-83A0-007FA8F03199",
  "exportOptions": {
    "_class": "exportOptions",
    "exportFormats": [
    ],
    "includedLayerIds": [
    ],
    "layerOptions": 0,
    "shouldTrim": false
  },
  "frame": {
    "_class": "rect",
    "constrainProportions": false,
    "height": 300,
    "width": 300,
    "x": 0,
    "y": 0
  },
  "grid": {
    "_class": "simpleGrid",
    "gridSize": 20,
    "isEnabled": false,
    "thickGridTimes": 10
  },
  "hasClickThrough": true,
  "horizontalRulerData": {
    "_class": "rulerData",
    "base": -580,
    "guides": [
    ]
  },
  "includeInCloudUpload": true,
  "isFlippedHorizontal": false,
  "isFlippedVertical": false,
  "isLocked": false,
  "isVisible": true,
  "layerListExpandedType": 0,
  "layers": [
    {
      "class": "artboard",
      "id": "53B0E052-AE4F-4ABC-B1FA-54ACC997741C"
    },
    {
      "class": "artboard",
      "id": "689D8B20-787D-4002-8DAC-F1EAEFEE038B"
    },
    {
      "class": "artboard",
      "id": "2C26DD3B-6C0A-4810-80FD-19590C23DD76"
    },
    {
      "class": "artboard",
      "id": "90365D59-5AE8-4813-AAD9-673D3C205947"
    },
    {
      "class": "artboard",
      "id": "C8198895-8B39-4C77-94BD-0474ECF16803"
    },
    {
      "class": "artboard",
      "id": "C722E49E-B035-4A9F-B954-0AFC2BD630DE"
    },
    {
      "class": "artboard",
      "id": "0A9816E5-8740-4CB3-A55F-F1A028E59F7D"
    },
    {
      "class": "artboard",
      "id": "C2900F67-52AB-493C-BFEF-EDFDDB3CC8ED"
    },
    {
      "class": "artboard",
      "id": "9F312390-EEC7-44F8-924E-FD2382256A30"
    },
    {
      "class": "artboard",
      "id": "FD863210-0CD7-424F-8B4F-194622B00F5B"
    },
    {
      "class": "artboard",
      "id": "F1EC6C65-2450-436A-BD3F-3F04920A0719"
    },
    {
      "class": "artboard",
      "id": "211A99B6-B894-472A-B529-355FCD172D77"
    },
    {
      "class": "artboard",
      "id": "2AE1F17E-24F3-4E45-A1E6-21961DE84280"
    },
    {
      "class": "artboard",
      "id": "438B6AF5-3739-4AFD-ADEE-B7D0DF735F55"
    },
    {
      "class": "artboard",
      "id": "1589B28E-1627-4A81-BE5F-226E583118A2"
    },
    {
      "class": "artboard",
      "id": "4BD82520-4DE4-47CE-ACF1-3927B34D11C8"
    },
    {
      "class": "artboard",
      "id": "4C1BC771-A110-4343-9CB0-AD77D99F6673"
    }
  ],
  "name": "Moderation user management",
  "nameIsFixed": true,
  "resizingConstraint": 63,
  "resizingType": 0,
  "rotation": 0,
  "shouldBreakMaskChain": false,
  "style": {
    "_class": "style",
    "endDecorationType": 0,
    "miterLimit": 10,
    "startDecorationType": 0
  },
  "verticalRulerData": {
    "_class": "rulerData",
    "base": -366,
    "guides": [
    ]
  }
}