{
  "_class": "group",
  "booleanOperation": 0,
  "do_objectID": "D154C1D7-9291-4D2C-8B6E-DE42943485B3",
  "exportOptions": {
    "_class": "exportOptions",
    "exportFormats": [
    ],
    "includedLayerIds": [
    ],
    "layerOptions": 0,
    "shouldTrim": false
  },
  "frame": {
    "_class": "rect",
    "constrainProportions": false,
    "height": 23,
    "width": 129,
    "x": 209,
    "y": 78
  },
  "hasClickThrough": false,
  "isFixedToViewport": false,
  "isFlippedHorizontal": false,
  "isFlippedVertical": false,
  "isLocked": false,
  "isVisible": true,
  "layerListExpandedType": 1,
  "layers": [
    {
      "class": "shapeGroup",
      "id": "5100CB0B-4048-4B75-AF3A-75AB6B535160"
    },
    {
      "class": "text",
      "id": "2521C92C-45D9-4B22-905A-C37667F6E463"
    }
  ],
  "name": "Dynamic group",
  "nameIsFixed": false,
  "resizingConstraint": 63,
  "resizingType": 0,
  "rotation": 0,
  "shouldBreakMaskChain": false,
  "style": {
    "_class": "style",
    "endMarkerType": 0,
    "miterLimit": 10,
    "startMarkerType": 0,
    "windingRule": 1
  }
}