{
  "_class": "group",
  "booleanOperation": 0,
  "do_objectID": "DA302F8C-E37B-4F87-9F1B-E564D51F17A3",
  "exportOptions": {
    "_class": "exportOptions",
    "exportFormats": [
    ],
    "includedLayerIds": [
    ],
    "layerOptions": 0,
    "shouldTrim": false
  },
  "frame": {
    "_class": "rect",
    "constrainProportions": false,
    "height": 28,
    "width": 101,
    "x": 1178,
    "y": 40
  },
  "hasClickThrough": false,
  "isFixedToViewport": false,
  "isFlippedHorizontal": false,
  "isFlippedVertical": false,
  "isLocked": false,
  "isVisible": false,
  "layerListExpandedType": 0,
  "layers": [
    {
      "class": "shapeGroup",
      "id": "E7B25A24-79D7-48F3-9E4D-EC64BA40A883"
    },
    {
      "class": "text",
      "id": "DC43743B-F87E-4EE5-8103-CD2FB2031128"
    }
  ],
  "name": "btn-edit-preprint",
  "nameIsFixed": true,
  "resizingConstraint": 63,
  "resizingType": 0,
  "rotation": 0,
  "shouldBreakMaskChain": false,
  "style": {
    "_class": "style",
    "endMarkerType": 0,
    "miterLimit": 10,
    "startMarkerType": 0,
    "windingRule": 1
  }
}