{
  "_class": "group",
  "do_objectID": "3304A5A6-AED2-4835-857A-9F10E1208A95",
  "exportOptions": {
    "_class": "exportOptions",
    "exportFormats": [
    ],
    "includedLayerIds": [
    ],
    "layerOptions": 0,
    "shouldTrim": false
  },
  "frame": {
    "_class": "rect",
    "constrainProportions": false,
    "height": 35,
    "width": 255.3541666666667,
    "x": 142.1972222222222,
    "y": 8
  },
  "hasClickThrough": false,
  "isFlippedHorizontal": false,
  "isFlippedVertical": false,
  "isLocked": false,
  "isVisible": true,
  "layerListExpandedType": 0,
  "layers": [
    {
      "class": "shapeGroup",
      "id": "4F742D13-80E4-42D0-82F6-F85598E039BA"
    },
    {
      "class": "bitmap",
      "id": "41BB9754-AE4D-408A-8145-2230594126A6"
    },
    {
      "class": "group",
      "id": "D17AFF78-B3EF-4B96-9FC6-5F8756FD60B0"
    }
  ],
  "name": "page-select",
  "nameIsFixed": true,
  "resizingConstraint": 63,
  "resizingType": 0,
  "rotation": 0,
  "shouldBreakMaskChain": false,
  "style": {
    "_class": "style",
    "endDecorationType": 0,
    "miterLimit": 10,
    "startDecorationType": 0
  }
}