{
  "_class": "group",
  "booleanOperation": -1,
  "do_objectID": "B4681F3A-E9C5-4877-8241-703975797C80",
  "exportOptions": {
    "_class": "exportOptions",
    "exportFormats": [
    ],
    "includedLayerIds": [
    ],
    "layerOptions": 0,
    "shouldTrim": false
  },
  "frame": {
    "_class": "rect",
    "constrainProportions": false,
    "height": 67,
    "width": 156,
    "x": 1123,
    "y": 75
  },
  "hasClickThrough": false,
  "isFixedToViewport": false,
  "isFlippedHorizontal": false,
  "isFlippedVertical": false,
  "isLocked": false,
  "isVisible": false,
  "layerListExpandedType": 0,
  "layers": [
    {
      "class": "shapeGroup",
      "id": "9C4F61A4-7920-4745-A8FA-3C6600429619"
    },
    {
      "class": "text",
      "id": "CCD8C238-26C7-4A2D-BAC7-8EDC29A2D868"
    },
    {
      "class": "text",
      "id": "422F14CE-7411-4E03-9432-333EB47D9AC2"
    }
  ],
  "name": "context-menu",
  "nameIsFixed": true,
  "resizingConstraint": 63,
  "resizingType": 0,
  "rotation": 0,
  "shouldBreakMaskChain": false,
  "style": {
    "_class": "style",
    "endMarkerType": 0,
    "miterLimit": 10,
    "startMarkerType": 0,
    "windingRule": 1
  }
}