{
  "_class": "group",
  "do_objectID": "626852BC-DE21-4266-ADB4-197336FE7184",
  "exportOptions": {
    "_class": "exportOptions",
    "exportFormats": [
    ],
    "includedLayerIds": [
    ],
    "layerOptions": 0,
    "shouldTrim": false
  },
  "frame": {
    "_class": "rect",
    "constrainProportions": false,
    "height": 54,
    "width": 1440,
    "x": 0,
    "y": 184
  },
  "hasClickThrough": false,
  "isFlippedHorizontal": false,
  "isFlippedVertical": false,
  "isLocked": false,
  "isVisible": true,
  "layerListExpandedType": 0,
  "layers": [
    {
      "class": "shapeGroup",
      "id": "53469795-3A3F-4952-BEFF-71D85C097F6F"
    },
    {
      "class": "text",
      "id": "88F43E7D-2F4F-48DE-9E07-04C7C8DA5FA3"
    }
  ],
  "name": "copyright",
  "nameIsFixed": true,
  "resizingConstraint": 63,
  "resizingType": 0,
  "rotation": 0,
  "shouldBreakMaskChain": false,
  "style": {
    "_class": "style",
    "endDecorationType": 0,
    "miterLimit": 10,
    "startDecorationType": 0
  }
}