{
  "_class": "symbolInstance",
  "do_objectID": "E244B818-5F54-4512-9500-E95324D2D24A",
  "exportOptions": {
    "_class": "exportOptions",
    "do_objectID": "7CF3F71C-09AD-4CB5-A3C2-486F4FD96C3A",
    "exportFormats": [
    ],
    "includedLayerIds": [
    ],
    "layerOptions": 0,
    "shouldTrim": false
  },
  "frame": {
    "_class": "rect",
    "constrainProportions": false,
    "do_objectID": "9098F2C3-AF7A-4794-A537-0578D9DE8B67",
    "height": 32.11000061035156,
    "width": 274,
    "x": 0,
    "y": 20
  },
  "horizontalSpacing": 0,
  "isFlippedHorizontal": false,
  "isFlippedVertical": false,
  "isLocked": false,
  "isVisible": true,
  "layerListExpandedType": 0,
  "name": "select-box",
  "nameIsFixed": false,
  "overrideValues": [
  ],
  "resizingConstraint": 63,
  "resizingType": 0,
  "rotation": 0,
  "scale": 1,
  "shouldBreakMaskChain": false,
  "style": {
    "_class": "style",
    "do_objectID": "0BCA14E8-DE03-49F3-9904-512AD8C3D128",
    "endDecorationType": 0,
    "miterLimit": 10,
    "startDecorationType": 0
  },
  "symbolID": "C517F0B1-2177-45FB-BFB9-10057FB00B39",
  "verticalSpacing": 0
}