{
  "_class": "group",
  "booleanOperation": 0,
  "do_objectID": "AC5282E6-ABB4-460F-BDE1-3083F199A247",
  "exportOptions": {
    "_class": "exportOptions",
    "exportFormats": [
    ],
    "includedLayerIds": [
    ],
    "layerOptions": 0,
    "shouldTrim": false
  },
  "frame": {
    "_class": "rect",
    "constrainProportions": false,
    "height": 230,
    "width": 748,
    "x": 1,
    "y": 0
  },
  "hasClickThrough": false,
  "isFixedToViewport": false,
  "isFlippedHorizontal": false,
  "isFlippedVertical": false,
  "isLocked": false,
  "isVisible": false,
  "layerListExpandedType": 0,
  "layers": [
    {
      "class": "shapeGroup",
      "id": "AEB6D14C-99C8-4DA1-82FE-11CFC90026FC"
    },
    {
      "class": "shapeGroup",
      "id": "C7159217-4F18-4089-82F1-758128ECA22D"
    },
    {
      "class": "shapeGroup",
      "id": "1488C46D-2D23-474D-AA23-17ED4A0956D5"
    },
    {
      "class": "shapeGroup",
      "id": "6CA95CC4-F773-449F-92D1-C456C64E4C1C"
    },
    {
      "class": "shapeGroup",
      "id": "E589D354-9563-45CD-B1E9-B9DE35A62A9C"
    },
    {
      "class": "shapeGroup",
      "id": "DEF6CB29-8B0D-4090-AD5B-1D9D2931A119"
    },
    {
      "class": "shapeGroup",
      "id": "4BA36792-98A3-449A-AEA6-150383F6DA75"
    },
    {
      "class": "shapeGroup",
      "id": "57F4AA81-9E22-4A28-825E-F18B22C708A9"
    },
    {
      "class": "shapeGroup",
      "id": "A6697C50-5D57-4F75-8E0D-DF63006875A6"
    },
    {
      "class": "shapeGroup",
      "id": "FB40F3C5-4ADD-4D98-B7F7-B9D9355D33ED"
    }
  ],
  "name": "padding",
  "nameIsFixed": true,
  "resizingConstraint": 63,
  "resizingType": 0,
  "rotation": 0,
  "shouldBreakMaskChain": false,
  "style": {
    "_class": "style",
    "endMarkerType": 0,
    "miterLimit": 10,
    "startMarkerType": 0,
    "windingRule": 1
  }
}