{
  "_class": "group",
  "do_objectID": "A2CC6018-D06B-4D23-9087-0A80A29F9ECD",
  "exportOptions": {
    "_class": "exportOptions",
    "exportFormats": [
    ],
    "includedLayerIds": [
    ],
    "layerOptions": 0,
    "shouldTrim": false
  },
  "frame": {
    "_class": "rect",
    "constrainProportions": false,
    "height": 23,
    "width": 68,
    "x": 344,
    "y": 52
  },
  "hasClickThrough": false,
  "isFlippedHorizontal": false,
  "isFlippedVertical": false,
  "isLocked": false,
  "isVisible": true,
  "layerListExpandedType": 0,
  "layers": [
    {
      "class": "shapeGroup",
      "id": "B09DF0CC-C53C-41E2-8A25-9F84BD107EB8"
    },
    {
      "class": "text",
      "id": "E85EF480-0ABC-43D2-8536-EC702A58F04F"
    }
  ],
  "name": "Dynamic group",
  "nameIsFixed": false,
  "resizingConstraint": 63,
  "resizingType": 0,
  "rotation": 0,
  "shouldBreakMaskChain": false,
  "style": {
    "_class": "style",
    "endDecorationType": 0,
    "miterLimit": 10,
    "startDecorationType": 0
  }
}