{
  "_class": "group",
  "booleanOperation": 0,
  "do_objectID": "DCFCEFBA-1B09-4F6F-AC0E-69BA2F1E97EC",
  "exportOptions": {
    "_class": "exportOptions",
    "exportFormats": [
    ],
    "includedLayerIds": [
    ],
    "layerOptions": 0,
    "shouldTrim": false
  },
  "frame": {
    "_class": "rect",
    "constrainProportions": false,
    "height": 720,
    "width": 1440,
    "x": 0,
    "y": 51
  },
  "hasClickThrough": false,
  "isFixedToViewport": false,
  "isFlippedHorizontal": false,
  "isFlippedVertical": false,
  "isLocked": false,
  "isVisible": true,
  "layerListExpandedType": 2,
  "layers": [
    {
      "class": "group",
      "id": "03199D8C-D30C-4B24-8FBD-F0F59CF82A8B"
    },
    {
      "class": "shapeGroup",
      "id": "546D24B0-2977-4446-92DB-44A015EEB816"
    },
    {
      "class": "shapeGroup",
      "id": "9457CDBE-40CD-4567-984E-AF7274675105"
    },
    {
      "class": "shapeGroup",
      "id": "08EC2291-2171-438E-8ED9-99EA37B7DD50"
    },
    {
      "class": "group",
      "id": "6E437FFC-4411-4527-BEFF-226BA5CBCD16"
    }
  ],
  "name": "preprint-detail-header",
  "nameIsFixed": false,
  "resizingConstraint": 63,
  "resizingType": 0,
  "rotation": 0,
  "shouldBreakMaskChain": false,
  "style": {
    "_class": "style",
    "endMarkerType": 0,
    "miterLimit": 10,
    "startMarkerType": 0,
    "windingRule": 1
  }
}