{
  "_class": "text",
  "attributedString": {
    "_class": "attributedString",
    "attributes": [
      {
        "_class": "stringAttribute",
        "attributes": {
          "MSAttributedStringColorAttribute": {
            "_class": "color",
            "alpha": 1,
            "blue": 0.4666666666666667,
            "green": 0.4666666666666667,
            "red": 0.4666666666666667
          },
          "MSAttributedStringFontAttribute": {
            "_class": "fontDescriptor",
            "attributes": {
              "name": "OpenSans-Light",
              "size": 14
            }
          },
          "paragraphStyle": {
            "_class": "paragraphStyle"
          }
        },
        "length": 303,
        "location": 0
      }
    ],
    "string": "Preferences that are products of introspection and endorsed by the respondent (explicit attitudes) can conflict with preferences that are measured indirectly and do not require conscious introspection or endorsement (implicit attitudes). In three studies, two factors are examined that may predict wh..."
  },
  "automaticallyDrawOnUnderlyingPath": false,
  "booleanOperation": 0,
  "do_objectID": "0F0035F7-768F-4A16-98C5-5536DFA2ABFF",
  "dontSynchroniseWithSymbol": false,
  "exportOptions": {
    "_class": "exportOptions",
    "exportFormats": [
    ],
    "includedLayerIds": [
    ],
    "layerOptions": 0,
    "shouldTrim": false
  },
  "frame": {
    "_class": "rect",
    "constrainProportions": false,
    "height": 62,
    "width": 728,
    "x": 11,
    "y": 134
  },
  "glyphBounds": "{{0, 4}, {719, 53}}",
  "isFixedToViewport": false,
  "isFlippedHorizontal": false,
  "isFlippedVertical": false,
  "isLocked": false,
  "isVisible": true,
  "layerListExpandedType": 0,
  "lineSpacingBehaviour": 2,
  "name": "Preferences that are",
  "nameIsFixed": false,
  "resizingConstraint": 45,
  "resizingType": 0,
  "rotation": 0,
  "shouldBreakMaskChain": false,
  "style": {
    "_class": "style",
    "endMarkerType": 0,
    "miterLimit": 10,
    "startMarkerType": 0,
    "textStyle": {
      "_class": "textStyle",
      "encodedAttributes": {
        "MSAttributedStringColorAttribute": {
          "_class": "color",
          "alpha": 1,
          "blue": 0.4666666666666667,
          "green": 0.4666666666666667,
          "red": 0.4666666666666667
        },
        "MSAttributedStringFontAttribute": {
          "_class": "fontDescriptor",
          "attributes": {
            "name": "OpenSans-Light",
            "size": 14
          }
        },
        "paragraphStyle": {
          "_class": "paragraphStyle"
        }
      },
      "verticalAlignment": 0
    },
    "windingRule": 1
  },
  "textBehaviour": 2,
  "userInfo": {
    "com.precious-forever.sketch.datapopulator": {
      "originalText": "{description}"
    }
  }
}